lastfmcollagegenerator/__init__.py
lastfmcollagegenerator/collage.py
lastfmcollagegenerator/collage_generator.py
lastfmcollagegenerator/constants.py
lastfmcollagegenerator/exceptions.py
lastfmcollagegenerator/fonts/DejaVuSansMono-Bold.ttf
lastfmcollagegenerator/fonts/DejaVuSansMono.ttf
lastfmcollagegenerator/lastfm/__init__.py
lastfmcollagegenerator/lastfm/client.py
lastfmcollagegenerator-0.4.13.dist-info/LICENSE
lastfmcollagegenerator-0.4.13.dist-info/METADATA
lastfmcollagegenerator-0.4.13.dist-info/WHEEL
lastfmcollagegenerator-0.4.13.dist-info/RECORD
