Metadata-Version: 2.1
Name: lastfmcollagegenerator
Version: 0.4.13
Summary: Python library to build Last.fm collages
Home-page: https://github.com/paurieraf/lastfm-collage-generator
Keywords: lastfm,music,collage,album,cover,artist,musicbucket,musicbucket.net
Author: Pau Riera
Author-email: pau.riera.forteza@gmail.com
Requires-Python: >=3.8,<4.0
Classifier: License :: OSI Approved :: MIT License
Classifier: Operating System :: OS Independent
Classifier: Programming Language :: Python :: 3
Classifier: Programming Language :: Python :: 3.8
Classifier: Programming Language :: Python :: 3.9
Classifier: Programming Language :: Python :: 3.10
Classifier: Programming Language :: Python :: 3.11
Classifier: Programming Language :: Python :: 3.12
Requires-Dist: Pillow (==10.4.0)
Requires-Dist: beautifulsoup4 (==4.12.3)
Requires-Dist: html5lib (==1.1)
Requires-Dist: pylast (==5.3.0)
Requires-Dist: requests (==2.32.3)
Project-URL: Bug Tracker, https://github.com/paurieraf/lastfm-collage-generator/issues
Project-URL: Repository, https://github.com/paurieraf/lastfm-collage-generator
